LICENSE
MANIFEST.in
README.rst
helga_alkafact.py
setup.py
helga_alkafact.egg-info/PKG-INFO
helga_alkafact.egg-info/SOURCES.txt
helga_alkafact.egg-info/dependency_links.txt
helga_alkafact.egg-info/entry_points.txt
helga_alkafact.egg-info/top_level.txt
helga_alkafact.egg-info/zip-safe